AUTHORS.md
CHANGES.md
LICENSE
MANIFEST.in
README.md
requirements.txt
setup.py
flask_pytest/__init__.py
flask_pytest.egg-info/PKG-INFO
flask_pytest.egg-info/SOURCES.txt
flask_pytest.egg-info/dependency_links.txt
flask_pytest.egg-info/requires.txt
flask_pytest.egg-info/top_level.txt