Metadata-Version: 1.0
Name: flask-pytest
Version: 0.0.4
Summary: Runs pytest in a background process when DEBUG is True.
Home-page: http://github.com/joeyespo/flask-pytest
Author: Joe Esposito
Author-email: joe@joeyespo.com
License: MIT
Platform: any
